juliacall/__init__.py
juliacall/importer.py
juliacall/init.jl
juliacall/ipython.py
juliacall/juliapkg-dev.json
juliacall/juliapkg.json
juliacall/matplotlib.py
juliacall-0.9.29.dist-info/METADATA
juliacall-0.9.29.dist-info/WHEEL
juliacall-0.9.29.dist-info/licenses/LICENSE
juliacall-0.9.29.dist-info/RECORD
