Metadata-Version: 2.4
Name: juliacall
Version: 0.9.29
Summary: Julia and Python in seamless harmony
License-File: LICENSE
Classifier: License :: OSI Approved :: MIT License
Classifier: Operating System :: OS Independent
Classifier: Programming Language :: Python :: 3
Requires-Python: <4,>=3.10
Requires-Dist: juliapkg<0.2,>=0.1.21
